<?xml version="1.0" encoding="utf-8" ?><dwsync><file name="android-chrome-192x192.png" server="ftp.alevzvs.com" local="3603197204" remote="3606271740" Dst="-1" /><file name="apple-touch-icon.png" server="ftp.alevzvs.com" local="3603197204" remote="3606271740" Dst="-1" /><file name="browserconfig.xml" server="ftp.alevzvs.com" local="3603197204" remote="3606271740" Dst="-1" /><file name="favicon-16x16.png" server="ftp.alevzvs.com" local="3603197206" remote="3606271800" Dst="-1" /><file name="favicon-32x32.png" server="ftp.alevzvs.com" local="3603197206" remote="3606271800" Dst="-1" /><file name="favicon.ico" server="ftp.alevzvs.com" local="3603197206" remote="3606271800" Dst="-1" /><file name="index.html" server="ftp.alevzvs.com" local="3606308311" remote="3606308880" Dst="-1" /><file name="mstile-150x150.png" server="ftp.alevzvs.com" local="3603197206" remote="3606271860" Dst="-1" /><file name="safari-pinned-tab.svg" server="ftp.alevzvs.com" local="3603197206" remote="3606271860" Dst="-1" /><file name="site.webmanifest" server="ftp.alevzvs.com" local="3603197206" remote="3606271860" Dst="-1" /><file name=".ftpquota" server="ftp.alevzvs.com" local="3604005660" remote="3604005660" Dst="-1" /></dwsync>